{
  "filters_applied": {
    "version": "FT New",
    "country": "ZZZ",
    "language": "eng",
    "domain": "APS"
  },
  "items": [
    {
      "item_id": "U101-Transport",
      "unit_name": "U101-Transport",
      "href": "",
      "tag": "LI"
    },
    {
      "item_id": "U102-GardenTime",
      "unit_name": "U102-GardenTime",
      "href": "",
      "tag": "LI"
    },
    {
      "item_id": "U103-ShiftRoster",
      "unit_name": "U103-ShiftRoster",
      "href": "",
      "tag": "LI"
    },
    {
      "item_id": "U104-EndofYearParty",
      "unit_name": "U104-EndofYearParty",
      "href": "",
      "tag": "LI"
    },
    {
      "item_id": "U105-Tickets",
      "unit_name": "U105-Tickets",
      "href": "",
      "tag": "LI"
    },
    {
      "item_id": "U106-Troubleshooting",
      "unit_name": "U106-Troubleshooting",
      "href": "",
      "tag": "LI"
    },
    {
      "item_id": "U107-ProductReturn",
      "unit_name": "U107-ProductReturn",
      "href": "",
      "tag": "LI"
    },
    {
      "item_id": "U108-PowerPlant",
      "unit_name": "U108-PowerPlant",
      "href": "",
      "tag": "LI"
    },
    {
      "item_id": "U109-TravelPlanning",
      "unit_name": "U109-TravelPlanning",
      "href": "",
      "tag": "LI"
    },
    {
      "item_id": "U110-Renovation",
      "unit_name": "U110-Renovation",
      "href": "",
      "tag": "LI"
    },
    {
      "item_id": "U111-PostOffice",
      "unit_name": "U111-PostOffice",
      "href": "",
      "tag": "LI"
    },
    {
      "item_id": "U112-Hiking",
      "unit_name": "U112-Hiking",
      "href": "",
      "tag": "LI"
    },
    {
      "item_id": "U113-Plumbing",
      "unit_name": "U113-Plumbing",
      "href": "",
      "tag": "LI"
    },
    {
      "item_id": "U114-ShipsAhoy",
      "unit_name": "U114-ShipsAhoy",
      "href": "",
      "tag": "LI"
    },
    {
      "item_id": "U115-TrafficControl",
      "unit_name": "U115-TrafficControl",
      "href": "",
      "tag": "LI"
    }
  ]
}